latentscope/__init__.py
latentscope/__version__.py
latentscope/models/__init__.py
latentscope/models/chat_models.json
latentscope/models/embedding_models.json
latentscope/models/providers/__init__.py
latentscope/models/providers/base.py
latentscope/models/providers/cohereai.py
latentscope/models/providers/mistralai.py
latentscope/models/providers/nltk.py
latentscope/models/providers/openai.py
latentscope/models/providers/prompts.py
latentscope/models/providers/togetherai.py
latentscope/models/providers/transformers.py
latentscope/models/providers/voyageai.py
latentscope/scripts/__init__.py
latentscope/scripts/cluster-1d.py
latentscope/scripts/cluster.py
latentscope/scripts/download_dataset.py
latentscope/scripts/embed.py
latentscope/scripts/export_plot.py
latentscope/scripts/ingest.py
latentscope/scripts/label_clusters.py
latentscope/scripts/sae.py
latentscope/scripts/scope.py
latentscope/scripts/umapper-1d.py
latentscope/scripts/umapper.py
latentscope/scripts/upload_dataset.py
latentscope/server/__init__.py
latentscope/server/admin.py
latentscope/server/app.py
latentscope/server/bulk.py
latentscope/server/datasets.py
latentscope/server/jobs.py
latentscope/server/models.py
latentscope/server/search.py
latentscope/server/tags.py
latentscope/util/__init__.py
latentscope/util/configuration.py
latentscope/web/dist/index.html
latentscope/web/dist/assets/hyparquet-CuRZSfcS.js
latentscope/web/dist/assets/index-1dsTsRCl.css
latentscope/web/dist/assets/index-Cp9ikwq4.js
latentscope-0.6.0.dist-info/LICENSE
latentscope-0.6.0.dist-info/METADATA
latentscope-0.6.0.dist-info/WHEEL
latentscope-0.6.0.dist-info/entry_points.txt
latentscope-0.6.0.dist-info/top_level.txt
latentscope-0.6.0.dist-info/RECORD
