Metadata-Version: 2.1
Name: latentscope
Version: 0.6.0
Summary: Quickly embed, project, cluster and explore a dataset.
Home-page: https://github.com/enjalot/latent-scope
License: UNKNOWN
Project-URL: Source, https://github.com/enjalot/latent-scope
Project-URL: Tracker, https://github.com/enjalot/latent-scope/issues
Platform: UNKNOWN
License-File: LICENSE
Requires-Dist: numpy (~=1.26.4)
Requires-Dist: accelerate (~=0.31.0)
Requires-Dist: aiohttp (~=3.9.1)
Requires-Dist: aiolimiter (~=1.1.0)
Requires-Dist: aiosignal (~=1.3.1)
Requires-Dist: annotated-types (~=0.6.0)
Requires-Dist: anyio (~=4.2.0)
Requires-Dist: appnope (~=0.1.3)
Requires-Dist: argon2-cffi (~=23.1.0)
Requires-Dist: argon2-cffi-bindings (~=21.2.0)
Requires-Dist: arrow (~=1.3.0)
Requires-Dist: asttokens (~=2.4.1)
Requires-Dist: async-lru (~=2.0.4)
Requires-Dist: attrs (~=23.2.0)
Requires-Dist: Babel (~=2.14.0)
Requires-Dist: backoff (~=2.2.1)
Requires-Dist: beautifulsoup4 (~=4.12.3)
Requires-Dist: bleach (~=6.1.0)
Requires-Dist: blinker (~=1.7.0)
Requires-Dist: certifi (~=2023.11.17)
Requires-Dist: cffi (~=1.16.0)
Requires-Dist: charset-normalizer (~=3.3.2)
Requires-Dist: click (~=8.1.7)
Requires-Dist: cohere (~=4.44)
Requires-Dist: comm (~=0.2.1)
Requires-Dist: contourpy
Requires-Dist: cycler (~=0.12.1)
Requires-Dist: Cython (~=0.29.37)
Requires-Dist: datamapplot (~=0.3.0)
Requires-Dist: debugpy (~=1.8.0)
Requires-Dist: decorator (~=5.1.1)
Requires-Dist: defusedxml (~=0.7.1)
Requires-Dist: distro (~=1.9.0)
Requires-Dist: einops (~=0.7.0)
Requires-Dist: executing (~=2.0.1)
Requires-Dist: fastavro (~=1.9.3)
Requires-Dist: fastjsonschema (~=2.19.1)
Requires-Dist: filelock (~=3.13.1)
Requires-Dist: Flask (~=3.0.0)
Requires-Dist: Flask-Cors (~=4.0.0)
Requires-Dist: fonttools (~=4.47.2)
Requires-Dist: fqdn (~=1.5.1)
Requires-Dist: frozenlist (~=1.4.1)
Requires-Dist: fsspec (~=2023.10.0)
Requires-Dist: h11 (~=0.14.0)
Requires-Dist: h5py
Requires-Dist: hdbscan
Requires-Dist: httpcore (~=1.0.2)
Requires-Dist: httpx (~=0.25.2)
Requires-Dist: huggingface-hub (~=0.24.5)
Requires-Dist: idna (~=3.6)
Requires-Dist: importlib-metadata (~=6.11.0)
Requires-Dist: ipykernel (~=6.29.0)
Requires-Dist: ipython (~=8.18.0)
Requires-Dist: ipywidgets (~=8.1.1)
Requires-Dist: isoduration (~=20.11.0)
Requires-Dist: itsdangerous (~=2.1.2)
Requires-Dist: jedi (~=0.19.1)
Requires-Dist: Jinja2 (~=3.1.3)
Requires-Dist: joblib (~=1.3.2)
Requires-Dist: json5 (~=0.9.14)
Requires-Dist: jsonpointer (~=2.4)
Requires-Dist: jsonschema (~=4.21.1)
Requires-Dist: jsonschema-specifications (~=2023.12.1)
Requires-Dist: jupyter (~=1.0.0)
Requires-Dist: jupyter-console (~=6.6.3)
Requires-Dist: jupyter-events (~=0.9.0)
Requires-Dist: jupyter-lsp (~=2.2.2)
Requires-Dist: jupyter-client (~=8.6.0)
Requires-Dist: jupyter-core (~=5.7.1)
Requires-Dist: jupyter-server (~=2.12.5)
Requires-Dist: jupyter-server-terminals (~=0.5.2)
Requires-Dist: jupyterlab (~=4.0.12)
Requires-Dist: jupyterlab-widgets (~=3.0.9)
Requires-Dist: jupyterlab-pygments (~=0.3.0)
Requires-Dist: jupyterlab-server (~=2.25.2)
Requires-Dist: kiwisolver (~=1.4.5)
Requires-Dist: latentsae (~=0.1.3)
Requires-Dist: llvmlite (~=0.42.0)
Requires-Dist: MarkupSafe (~=2.1.3)
Requires-Dist: matplotlib
Requires-Dist: matplotlib-inline
Requires-Dist: mistralai (~=0.0.11)
Requires-Dist: mistune (~=3.0.2)
Requires-Dist: mpmath (~=1.3.0)
Requires-Dist: multidict (~=6.0.4)
Requires-Dist: nbclient (~=0.9.0)
Requires-Dist: nbconvert (~=7.14.2)
Requires-Dist: nbformat (~=5.9.2)
Requires-Dist: nest-asyncio (~=1.5.9)
Requires-Dist: networkx (~=3.2.1)
Requires-Dist: nltk (~=3.8.1)
Requires-Dist: notebook (~=7.0.7)
Requires-Dist: notebook-shim (~=0.2.3)
Requires-Dist: numba (~=0.59.0)
Requires-Dist: openai (~=1.12.0)
Requires-Dist: opt-einsum
Requires-Dist: orjson (~=3.9.12)
Requires-Dist: outlines (~=0.1.0)
Requires-Dist: overrides (~=7.7.0)
Requires-Dist: packaging (~=23.2)
Requires-Dist: pandas
Requires-Dist: pandocfilters (~=1.5.1)
Requires-Dist: parso (~=0.8.3)
Requires-Dist: pexpect (~=4.9.0)
Requires-Dist: pillow (~=10.2.0)
Requires-Dist: platformdirs (~=4.1.0)
Requires-Dist: prometheus-client (~=0.19.0)
Requires-Dist: prompt-toolkit (~=3.0.43)
Requires-Dist: psutil (~=5.9.7)
Requires-Dist: ptyprocess (~=0.7.0)
Requires-Dist: pure-eval (~=0.2.2)
Requires-Dist: pyarrow (~=17.0.0)
Requires-Dist: pycparser (~=2.21)
Requires-Dist: pydantic (~=2.5.3)
Requires-Dist: pydantic-core (~=2.14.6)
Requires-Dist: Pygments (~=2.17.2)
Requires-Dist: pynndescent (~=0.5.11)
Requires-Dist: pyparsing (~=3.1.1)
Requires-Dist: python-dateutil (~=2.8.2)
Requires-Dist: python-dotenv (~=1.0.0)
Requires-Dist: python-json-logger (~=2.0.7)
Requires-Dist: pytz (~=2023.3.post1)
Requires-Dist: PyYAML (~=6.0.1)
Requires-Dist: pyzmq (~=25.1.2)
Requires-Dist: qtconsole (~=5.5.1)
Requires-Dist: QtPy (~=2.4.1)
Requires-Dist: referencing (~=0.33.0)
Requires-Dist: regex (~=2023.12.25)
Requires-Dist: requests (~=2.32.0)
Requires-Dist: rfc3339-validator (~=0.1.4)
Requires-Dist: rfc3986-validator (~=0.1.1)
Requires-Dist: rpds-py (~=0.17.1)
Requires-Dist: safetensors (~=0.4.1)
Requires-Dist: scikit-learn (~=1.3.2)
Requires-Dist: scipy (~=1.11.4)
Requires-Dist: Send2Trash (~=1.8.2)
Requires-Dist: sentence-transformers (~=3.2.0)
Requires-Dist: six (~=1.16.0)
Requires-Dist: sniffio (~=1.3.0)
Requires-Dist: soupsieve (~=2.5)
Requires-Dist: sseclient-py (~=1.8.0)
Requires-Dist: stack-data (~=0.6.3)
Requires-Dist: sympy (~=1.12)
Requires-Dist: tabulate (~=0.9.0)
Requires-Dist: tenacity (~=8.2.3)
Requires-Dist: terminado (~=0.18.0)
Requires-Dist: threadpoolctl (~=3.2.0)
Requires-Dist: tiktoken (~=0.7.0)
Requires-Dist: tinycss2 (~=1.2.1)
Requires-Dist: together (~=0.2.10)
Requires-Dist: tokenizers (~=0.20.0)
Requires-Dist: torch (~=2.3.0)
Requires-Dist: tornado (~=6.4)
Requires-Dist: tqdm (~=4.66.1)
Requires-Dist: traitlets (~=5.14.1)
Requires-Dist: transformers (~=4.46.3)
Requires-Dist: typer (~=0.9.0)
Requires-Dist: types-python-dateutil (~=2.8.19.20240106)
Requires-Dist: typing-extensions (~=4.9.0)
Requires-Dist: tzdata (~=2023.4)
Requires-Dist: umap-learn (~=0.5.5)
Requires-Dist: uri-template (~=1.3.0)
Requires-Dist: urllib3 (~=2.1.0)
Requires-Dist: voyageai (~=0.2.3)
Requires-Dist: wcwidth (~=0.2.13)
Requires-Dist: webcolors (~=1.13)
Requires-Dist: webencodings (~=0.5.1)
Requires-Dist: websocket-client (~=1.7.0)
Requires-Dist: Werkzeug (~=3.0.1)
Requires-Dist: widgetsnbextension (~=4.0.9)
Requires-Dist: yarl (~=1.9.4)
Requires-Dist: zipp (~=3.17.0)
Requires-Dist: lancedb (~=0.19.0)
